dataligo/__init__.py
dataligo/core.py
dataligo/exceptions.py
dataligo/utils.py
dataligo/databases/__init__.py
dataligo/databases/database.py
dataligo/datalakes/__init__.py
dataligo/datalakes/datalake.py
dataligo/datalakes/utils.py
dataligo/datawarehouses/__init__.py
dataligo/datawarehouses/datawarehouse.py
dataligo/datawarehouses/utils.py
dataligo/nosql/__init__.py
dataligo/nosql/nosql.py
dataligo-0.7.3.dist-info/LICENSE
dataligo-0.7.3.dist-info/METADATA
dataligo-0.7.3.dist-info/WHEEL
dataligo-0.7.3.dist-info/top_level.txt
dataligo-0.7.3.dist-info/RECORD
