Metadata-Version: 2.1
Name: dataligo
Version: 0.7.3
Summary: A library to accelerate ML and ETL pipeline by connecting all data sources
Author-email: Vinish M <vinishuchiha@gmail.com>
License: Apache License
Project-URL: Homepage, https://github.com/VinishUchiha/dataligo
Keywords: connectors,datalake reader,datawarehouse reader,dataconnector,nosql connector
Classifier: License :: OSI Approved :: Apache Software License
Classifier: Programming Language :: Python
Classifier: Programming Language :: Python :: 3
Requires-Python: >=3.7
License-File: LICENSE
Requires-Dist: boto3 (>=1.26.93)
Requires-Dist: google-cloud-storage (>=2.7.0)
Requires-Dist: azure-storage-blob (>=12.15.0)
Requires-Dist: pandas (>=1.0.0)
Requires-Dist: PyYAML
Requires-Dist: connectorx
Requires-Dist: snowflake-connector-python[pandas] (==3.0.2)
Requires-Dist: mysql-connector-python-rf
Requires-Dist: sqlalchemy (==1.4.46)
Requires-Dist: tomli ; python_version < "3.11"
Provides-Extra: all
Requires-Dist: polars ; extra == 'all'
Requires-Dist: elasticsearch (>8.0.0) ; extra == 'all'
Requires-Dist: pymongo ; extra == 'all'
Requires-Dist: dynamo-pandas ; extra == 'all'
Provides-Extra: dev
Requires-Dist: black ; extra == 'dev'
Requires-Dist: bumpver ; extra == 'dev'
Requires-Dist: isort ; extra == 'dev'
Requires-Dist: pip-tools ; extra == 'dev'
Requires-Dist: pytest ; extra == 'dev'
Provides-Extra: dynamodb
Requires-Dist: dynamo-pandas ; extra == 'dynamodb'
Provides-Extra: elasticsearch
Requires-Dist: elasticsearch (>8.0.0) ; extra == 'elasticsearch'
Provides-Extra: mongodb
Requires-Dist: pymongo ; extra == 'mongodb'
Provides-Extra: polars
Requires-Dist: polars ; extra == 'polars'
